pytest_pgsql/__init__.py
pytest_pgsql/database.py
pytest_pgsql/errors.py
pytest_pgsql/ext.py
pytest_pgsql/plugin.py
pytest_pgsql/time.py
pytest_pgsql/version.py
pytest_pgsql/tests/__init__.py
pytest_pgsql/tests/conftest.py
pytest_pgsql/tests/database_test.py
pytest_pgsql/tests/ext_test.py
pytest_pgsql/tests/plugin_test.py
pytest_pgsql/tests/time_test.py
pytest_pgsql-1.1.2.dist-info/DESCRIPTION.rst
pytest_pgsql-1.1.2.dist-info/METADATA
pytest_pgsql-1.1.2.dist-info/RECORD
pytest_pgsql-1.1.2.dist-info/WHEEL
pytest_pgsql-1.1.2.dist-info/entry_points.txt
pytest_pgsql-1.1.2.dist-info/metadata.json
pytest_pgsql-1.1.2.dist-info/pbr.json
pytest_pgsql-1.1.2.dist-info/top_level.txt
