Metadata-Version: 2.0
Name: pytest-pgsql
Version: 1.1.2
Summary: Pytest plugins and helpers for tests using a Postgres database.
Home-page: https://github.com/CloverHealth/pytest-pgsql
Author: Clover Health
Author-email: dev@cloverhealth.com
License: Copyright Clover Health, Inc.
Platform: UNKNOWN
Classifier: Development Status :: 5 - Production/Stable
Classifier: Framework :: Pytest
Classifier: Intended Audience :: Developers
Classifier: License :: OSI Approved :: BSD License
Classifier: Operating System :: OS Independent
Classifier: Programming Language :: Python
Classifier: Programming Language :: Python :: 3
Classifier: Programming Language :: Python :: 3.4
Classifier: Programming Language :: Python :: 3.5
Classifier: Programming Language :: Python :: 3.6
Classifier: Topic :: Database
Classifier: Topic :: Software Development :: Testing
Requires-Dist: freezegun (>=0.3.6)
Requires-Dist: pytest (>=3.0.0)
Requires-Dist: sqlalchemy (>=1.1.0)
Requires-Dist: testing.postgresql (>=1.3.0)
